{"en":{"verses":[{"id":1,"segments":[{"t":"Now","s":"H428"},{"t":" ","s":null},{"t":"the","s":"H4428"},{"t":"se ","s":null},{"t":"are","s":"H776"},{"t":" the ","s":null},{"t":"kings","s":"H1121"},{"t":" ","s":null},{"t":"of","s":"H4217"},{"t":" the ","s":null},{"t":"land","s":"H769"},{"t":" ","s":null},{"t":"whom","s":"H6160"},{"t":" the children of Israel ","s":null},{"t":"overcame","s":"H5221"},{"t":", taking ","s":null},{"t":"as","s":"H834"},{"t":" ","s":null},{"t":"their","s":"H3423"},{"t":" heritage their land ","s":null},{"t":"on","s":"H5676"},{"t":" the east ","s":null},{"t":"side","s":"H5704"},{"t":" of Jordan, from the valley of the ","s":null},{"t":"Arnon","s":"H5158"},{"t":" to ","s":null},{"t":"Mount","s":"H2022"},{"t":" ","s":null},{"t":"Hermon","s":"H2768"},{"t":", and all the Arabah to the east:","s":null}],"text":"Now these are the kings of the land whom the children of Israel overcame, taking as their heritage their land on the east side of Jordan, from the valley of the Arnon to Mount Hermon, and all the Arabah to the east:"},{"id":2,"segments":[{"t":"Sihon","s":"H5511"},{"t":", ","s":null},{"t":"king","s":"H4428"},{"t":" ","s":null},{"t":"of","s":"H567"},{"t":" ","s":null},{"t":"the","s":"H769"},{"t":" ","s":null},{"t":"Amorites","s":"H8193"},{"t":", ","s":null},{"t":"who","s":"H8432"},{"t":" ","s":null},{"t":"was","s":"H3427"},{"t":" ","s":null},{"t":"living","s":"H2999"},{"t":" in ","s":null},{"t":"Heshbon","s":"H1366"},{"t":", ","s":null},{"t":"ruling","s":"H1121"},{"t":" ","s":null},{"t":"from","s":"H4910"},{"t":" ","s":null},{"t":"Aroer","s":"H1568"},{"t":", ","s":null},{"t":"which","s":"H6177"},{"t":" is on the edge of the valley of the ","s":null},{"t":"Arnon","s":"H5158"},{"t":", and the town in the ","s":null},{"t":"middle","s":"H5704"},{"t":" of the valley, and half Gilead, as far as the river ","s":null},{"t":"Jabbok","s":"H5983"},{"t":", the ","s":null},{"t":"limits","s":"H2677"},{"t":" of the children of Ammon;","s":null}],"text":"Sihon, king of the Amorites, who was living in Heshbon, ruling from Aroer, which is on the edge of the valley of the Arnon, and the town in the middle of the valley, and half Gilead, as far as the river Jabbok, the limits of the children of Ammon;"},{"id":3,"segments":[{"t":"And","s":"H6160"},{"t":" ","s":null},{"t":"the","s":"H4217"},{"t":" ","s":null},{"t":"Arabah","s":"H794"},{"t":" ","s":null},{"t":"to","s":"H3220"},{"t":" the ","s":null},{"t":"sea","s":"H3672"},{"t":" ","s":null},{"t":"of","s":"H5704"},{"t":" ","s":null},{"t":"Chinneroth","s":"H6449"},{"t":", to the east, ","s":null},{"t":"and","s":"H1870"},{"t":" to the sea of the Arabah, that is the Salt Sea, to the east, the way to Beth-jeshimoth; and ","s":null},{"t":"on","s":"H1020"},{"t":" the ","s":null},{"t":"south","s":"H8486"},{"t":", ","s":null},{"t":"under","s":"H8478"},{"t":" the slopes of Pisgah:","s":null}],"text":"And the Arabah to the sea of Chinneroth, to the east, and to the sea of the Arabah, that is the Salt Sea, to the east, the way to Beth-jeshimoth; and on the south, under the slopes of Pisgah:"},{"id":4,"segments":[{"t":"And","s":"H1366"},{"t":" ","s":null},{"t":"the","s":"H5747"},{"t":" ","s":null},{"t":"land","s":"H4428"},{"t":" ","s":null},{"t":"of","s":"H1316"},{"t":" ","s":null},{"t":"Og","s":"H3499"},{"t":", ","s":null},{"t":"king","s":"H7497"},{"t":" of ","s":null},{"t":"Bashan","s":"H154"},{"t":", of the rest of the Rephaim, who was living ","s":null},{"t":"at","s":"H3427"},{"t":" ","s":null},{"t":"Ashtaroth","s":"H6252"},{"t":" and at Edrei,","s":null}],"text":"And the land of Og, king of Bashan, of the rest of the Rephaim, who was living at Ashtaroth and at Edrei,"},{"id":5,"segments":[{"t":"Ruling","s":"H4910"},{"t":" in ","s":null},{"t":"the","s":"H2022"},{"t":" ","s":null},{"t":"mountain","s":"H1568"},{"t":" ","s":null},{"t":"of","s":"H1651"},{"t":" ","s":null},{"t":"Hermon","s":"H2768"},{"t":", ","s":null},{"t":"and","s":"H5548"},{"t":" in ","s":null},{"t":"Salecah","s":"H1316"},{"t":", and in ","s":null},{"t":"all","s":"H5704"},{"t":" ","s":null},{"t":"Bashan","s":"H1366"},{"t":", as ","s":null},{"t":"far","s":"H2809"},{"t":" as the ","s":null},{"t":"limits","s":"H4602"},{"t":" of the ","s":null},{"t":"Geshurites","s":"H2677"},{"t":" and the Maacathites, and half Gilead, to the land of ","s":null},{"t":"Sihon","s":"H4428"},{"t":", king of Heshbon.","s":null}],"text":"Ruling in the mountain of Hermon, and in Salecah, and in all Bashan, as far as the limits of the Geshurites and the Maacathites, and half Gilead, to the land of Sihon, king of Heshbon."},{"id":6,"segments":[{"t":"Moses","s":"H4872"},{"t":", ","s":null},{"t":"the","s":"H5650"},{"t":" ","s":null},{"t":"servant","s":"H1121"},{"t":" ","s":null},{"t":"of","s":"H5221"},{"t":" the ","s":null},{"t":"Lord","s":"H3068"},{"t":", ","s":null},{"t":"and","s":"H5414"},{"t":" the ","s":null},{"t":"children","s":"H7206"},{"t":" of ","s":null},{"t":"Israel","s":"H1425"},{"t":" ","s":null},{"t":"overcame","s":"H2677"},{"t":" ","s":null},{"t":"them","s":"H3425"},{"t":"; and Moses, the servant of the Lord, ","s":null},{"t":"gave","s":"H4519"},{"t":" their land for a heritage to the Reubenites, and the Gadites, and the half-tribe of Manasseh.","s":null}],"text":"Moses, the servant of the Lord, and the children of Israel overcame them; and Moses, the servant of the Lord, gave their land for a heritage to the Reubenites, and the Gadites, and the half-tribe of Manasseh."},{"id":7,"segments":[{"t":"And","s":"H428"},{"t":" ","s":null},{"t":"the","s":"H4428"},{"t":"se ","s":null},{"t":"are","s":"H776"},{"t":" the ","s":null},{"t":"kings","s":"H3383"},{"t":" ","s":null},{"t":"of","s":"H3220"},{"t":" the ","s":null},{"t":"land","s":"H1237"},{"t":" ","s":null},{"t":"whom","s":"H3844"},{"t":" ","s":null},{"t":"Joshua","s":"H834"},{"t":" and the ","s":null},{"t":"children","s":"H4256"},{"t":" of ","s":null},{"t":"Israel","s":"H5221"},{"t":" ","s":null},{"t":"overcame","s":"H5676"},{"t":" ","s":null},{"t":"on","s":"H7626"},{"t":" the ","s":null},{"t":"west","s":"H3478"},{"t":" ","s":null},{"t":"side","s":"H5704"},{"t":" of Jordan, ","s":null},{"t":"from","s":"H1171"},{"t":" Baal-gad in the valley of Lebanon ","s":null},{"t":"to","s":"H8165"},{"t":" Mount ","s":null},{"t":"Halak","s":"H2022"},{"t":", ","s":null},{"t":"which","s":"H2510"},{"t":" ","s":null},{"t":"goes","s":"H5927"},{"t":" up to Seir; and Joshua gave the land to the tribes of Israel for a heritage, in ","s":null},{"t":"keeping","s":"H3425"},{"t":" with their divisions;","s":null}],"text":"And these are the kings of the land whom Joshua and the children of Israel overcame on the west side of Jordan, from Baal-gad in the valley of Lebanon to Mount Halak, which goes up to Seir; and Joshua gave the land to the tribes of Israel for a heritage, in keeping with their divisions;"},{"id":8,"segments":[{"t":"In","s":"H2022"},{"t":" ","s":null},{"t":"the","s":"H8219"},{"t":" ","s":null},{"t":"hill-country","s":"H6160"},{"t":", ","s":null},{"t":"and","s":"H794"},{"t":" ","s":null},{"t":"in","s":"H4057"},{"t":" the ","s":null},{"t":"lowland","s":"H5045"},{"t":", and in the ","s":null},{"t":"Arabah","s":"H2850"},{"t":", and on the mountain slopes, and in the waste land, and in the ","s":null},{"t":"South","s":"H2983"},{"t":"; the Hittites, the Amorites, and the ","s":null},{"t":"Canaanites","s":"H567"},{"t":", the ","s":null},{"t":"Perizzites","s":"H3669"},{"t":", the ","s":null},{"t":"Hivites","s":"H6522"},{"t":", and the ","s":null},{"t":"Jebusites","s":"H2340"},{"t":".","s":null}],"text":"In the hill-country, and in the lowland, and in the Arabah, and on the mountain slopes, and in the waste land, and in the South; the Hittites, the Amorites, and the Canaanites, the Perizzites, the Hivites, and the Jebusites."},{"id":9,"segments":[{"t":"The","s":"H4428"},{"t":" ","s":null},{"t":"king","s":"H5857"},{"t":" ","s":null},{"t":"of","s":"H3405"},{"t":" Jericho, ","s":null},{"t":"one","s":"H259"},{"t":"; the king of ","s":null},{"t":"Ai","s":"H834"},{"t":", which ","s":null},{"t":"is","s":"H6654"},{"t":" ","s":null},{"t":"near","s":"H1008"},{"t":" Beth-el, one;","s":null}],"text":"The king of Jericho, one; the king of Ai, which is near Beth-el, one;"},{"id":10,"segments":[{"t":"The","s":"H4428"},{"t":" ","s":null},{"t":"king","s":"H2275"},{"t":" ","s":null},{"t":"of","s":"H3389"},{"t":" Jerusalem, ","s":null},{"t":"one","s":"H259"},{"t":"; the king of Hebron, one;","s":null}],"text":"The king of Jerusalem, one; the king of Hebron, one;"},{"id":11,"segments":[{"t":"The","s":"H4428"},{"t":" ","s":null},{"t":"king","s":"H3923"},{"t":" ","s":null},{"t":"of","s":"H3412"},{"t":" Jarmuth, ","s":null},{"t":"one","s":"H259"},{"t":"; the king of Lachish, one;","s":null}],"text":"The king of Jarmuth, one; the king of Lachish, one;"},{"id":12,"segments":[{"t":"The","s":"H4428"},{"t":" ","s":null},{"t":"king","s":"H1507"},{"t":" ","s":null},{"t":"of","s":"H5700"},{"t":" Eglon, ","s":null},{"t":"one","s":"H259"},{"t":"; the king of Gezer, one;","s":null}],"text":"The king of Eglon, one; the king of Gezer, one;"},{"id":13,"segments":[{"t":"The","s":"H4428"},{"t":" ","s":null},{"t":"king","s":"H1445"},{"t":" ","s":null},{"t":"of","s":"H1688"},{"t":" Debir, ","s":null},{"t":"one","s":"H259"},{"t":"; the king of Geder, one;","s":null}],"text":"The king of Debir, one; the king of Geder, one;"},{"id":14,"segments":[{"t":"The","s":"H4428"},{"t":" ","s":null},{"t":"king","s":"H6166"},{"t":" ","s":null},{"t":"of","s":"H2767"},{"t":" Hormah, ","s":null},{"t":"one","s":"H259"},{"t":"; the king of Arad, one;","s":null}],"text":"The king of Hormah, one; the king of Arad, one;"},{"id":15,"segments":[{"t":"The","s":"H4428"},{"t":" ","s":null},{"t":"king","s":"H5725"},{"t":" ","s":null},{"t":"of","s":"H3841"},{"t":" Libnah, ","s":null},{"t":"one","s":"H259"},{"t":"; the king of Adullam, one;","s":null}],"text":"The king of Libnah, one; the king of Adullam, one;"},{"id":16,"segments":[{"t":"The","s":"H4428"},{"t":" ","s":null},{"t":"king","s":"H1008"},{"t":" ","s":null},{"t":"of","s":"H4719"},{"t":" Makkedah, ","s":null},{"t":"one","s":"H259"},{"t":"; the king of Beth-el, one;","s":null}],"text":"The king of Makkedah, one; the king of Beth-el, one;"},{"id":17,"segments":[{"t":"The","s":"H4428"},{"t":" ","s":null},{"t":"king","s":"H2660"},{"t":" ","s":null},{"t":"of","s":"H8599"},{"t":" Tappuah, ","s":null},{"t":"one","s":"H259"},{"t":"; the king of Hepher, one;","s":null}],"text":"The king of Tappuah, one; the king of Hepher, one;"},{"id":18,"segments":[{"t":"The","s":"H4428"},{"t":" ","s":null},{"t":"king","s":"H8289"},{"t":" ","s":null},{"t":"of","s":"H663"},{"t":" Aphek, ","s":null},{"t":"one","s":"H259"},{"t":"; the king of Lassharon, one;","s":null}],"text":"The king of Aphek, one; the king of Lassharon, one;"},{"id":19,"segments":[{"t":"The","s":"H4428"},{"t":" ","s":null},{"t":"king","s":"H2674"},{"t":" ","s":null},{"t":"of","s":"H4068"},{"t":" Madon, ","s":null},{"t":"one","s":"H259"},{"t":"; the king of Hazor, one;","s":null}],"text":"The king of Madon, one; the king of Hazor, one;"},{"id":20,"segments":[{"t":"The","s":"H4428"},{"t":" ","s":null},{"t":"king","s":"H407"},{"t":" ","s":null},{"t":"of","s":"H8112"},{"t":" Shimron-meron, ","s":null},{"t":"one","s":"H259"},{"t":"; the king of Achshaph, one;","s":null}],"text":"The king of Shimron-meron, one; the king of Achshaph, one;"},{"id":21,"segments":[{"t":"The","s":"H4428"},{"t":" ","s":null},{"t":"king","s":"H4023"},{"t":" ","s":null},{"t":"of","s":"H8590"},{"t":" Taanach, ","s":null},{"t":"one","s":"H259"},{"t":"; the king of Megiddo, one;","s":null}],"text":"The king of Taanach, one; the king of Megiddo, one;"},{"id":22,"segments":[{"t":"The","s":"H4428"},{"t":" ","s":null},{"t":"king","s":"H3362"},{"t":" ","s":null},{"t":"of","s":"H6943"},{"t":" Kedesh, ","s":null},{"t":"one","s":"H259"},{"t":"; the king of ","s":null},{"t":"Jokneam","s":"H3760"},{"t":" in Carmel, one;","s":null}],"text":"The king of Kedesh, one; the king of Jokneam in Carmel, one;"},{"id":23,"segments":[{"t":"The","s":"H4428"},{"t":" ","s":null},{"t":"king","s":"H1756"},{"t":" ","s":null},{"t":"of","s":"H1471"},{"t":" ","s":null},{"t":"Dor","s":"H1537"},{"t":" on ","s":null},{"t":"the","s":"H259"},{"t":" hill of Dor, one; the king of Goiim in Gilgal, one;","s":null}],"text":"The king of Dor on the hill of Dor, one; the king of Goiim in Gilgal, one;"},{"id":24,"segments":[{"t":"The","s":"H4428"},{"t":" king ","s":null},{"t":"of","s":"H8656"},{"t":" Tirzah, ","s":null},{"t":"one","s":"H259"},{"t":"; ","s":null},{"t":"all","s":"H7970"},{"t":" the kings ","s":null},{"t":"together","s":"H3605"},{"t":" were thirty-one.","s":null}],"text":"The king of Tirzah, one; all the kings together were thirty-one."}]},"fr":{"verses":[{"id":1,"segments":[{"t":"Or","s":"H428"},{"t":", ","s":null},{"t":"voici","s":"H3383"},{"t":" ","s":null},{"t":"les","s":"H776"},{"t":" ","s":null},{"t":"rois","s":"H4428"},{"t":" ","s":null},{"t":"du","s":"H1121"},{"t":" ","s":null},{"t":"pays","s":"H4217"},{"t":", ","s":null},{"t":"que","s":"H769"},{"t":" les ","s":null},{"t":"enfants","s":"H6160"},{"t":" d'Israël battirent, ","s":null},{"t":"et","s":"H3605"},{"t":" ","s":null},{"t":"dont","s":"H5221"},{"t":" ils ","s":null},{"t":"possédèrent","s":"H834"},{"t":" le pays, ","s":null},{"t":"au","s":"H3423"},{"t":" delà du ","s":null},{"t":"Jourdain","s":"H5676"},{"t":", vers le ","s":null},{"t":"soleil","s":"H5704"},{"t":" levant, depuis le torrent de ","s":null},{"t":"l'Arnon","s":"H5158"},{"t":" jusqu'à ","s":null},{"t":"la","s":"H2022"},{"t":" montagne ","s":null},{"t":"d'Hermon","s":"H2768"},{"t":", et toute la plaine à l'Orient:","s":null}],"text":"Or, voici les rois du pays, que les enfants d'Israël battirent, et dont ils possédèrent le pays, au delà du Jourdain, vers le soleil levant, depuis le torrent de l'Arnon jusqu'à la montagne d'Hermon, et toute la plaine à l'Orient:"},{"id":2,"segments":[{"t":"Sihon","s":"H5511"},{"t":", ","s":null},{"t":"roi","s":"H4428"},{"t":" ","s":null},{"t":"des","s":"H567"},{"t":" ","s":null},{"t":"Amoréens","s":"H8193"},{"t":", ","s":null},{"t":"qui","s":"H5921"},{"t":" ","s":null},{"t":"habitait","s":"H3427"},{"t":" ","s":null},{"t":"à","s":"H2809"},{"t":" ","s":null},{"t":"Hesbon","s":"H769"},{"t":". ","s":null},{"t":"Il","s":"H4910"},{"t":" ","s":null},{"t":"dominait","s":"H8432"},{"t":" ","s":null},{"t":"depuis","s":"H6177"},{"t":" ","s":null},{"t":"Aroër","s":"H2999"},{"t":" qui ","s":null},{"t":"est","s":"H1366"},{"t":" ","s":null},{"t":"au","s":"H1121"},{"t":" ","s":null},{"t":"bord","s":"H1568"},{"t":" du ","s":null},{"t":"torrent","s":"H5704"},{"t":" de l'Arnon et au milieu du torrent, et sur la moitié de Galaad, ","s":null},{"t":"jusqu'au","s":"H5983"},{"t":" torrent de ","s":null},{"t":"Jabbok","s":"H2677"},{"t":", frontière des enfants d'Ammon;","s":null}],"text":"Sihon, roi des Amoréens, qui habitait à Hesbon. Il dominait depuis Aroër qui est au bord du torrent de l'Arnon et au milieu du torrent, et sur la moitié de Galaad, jusqu'au torrent de Jabbok, frontière des enfants d'Ammon;"},{"id":3,"segments":[{"t":"Sur","s":"H6160"},{"t":" ","s":null},{"t":"la","s":"H4217"},{"t":" ","s":null},{"t":"plaine","s":"H3220"},{"t":" ","s":null},{"t":"jusqu'à","s":"H794"},{"t":" la ","s":null},{"t":"mer","s":"H3672"},{"t":" ","s":null},{"t":"de","s":"H5704"},{"t":" ","s":null},{"t":"Kinnéreth","s":"H6449"},{"t":", vers l'orient, et jusqu'à la mer de la plaine, la mer Salée, à l'orient, dans la direction de Beth-Jeshimoth; et ","s":null},{"t":"du","s":"H1020"},{"t":" ","s":null},{"t":"côté","s":"H1870"},{"t":" du ","s":null},{"t":"midi","s":"H8486"},{"t":", ","s":null},{"t":"sous","s":"H8478"},{"t":" les pentes du Pisga.","s":null}],"text":"Sur la plaine jusqu'à la mer de Kinnéreth, vers l'orient, et jusqu'à la mer de la plaine, la mer Salée, à l'orient, dans la direction de Beth-Jeshimoth; et du côté du midi, sous les pentes du Pisga."},{"id":4,"segments":[{"t":"Et","s":"H1366"},{"t":" ","s":null},{"t":"le","s":"H5747"},{"t":" ","s":null},{"t":"territoire","s":"H1316"},{"t":" ","s":null},{"t":"d'Og","s":"H3499"},{"t":", ","s":null},{"t":"roi","s":"H4428"},{"t":" ","s":null},{"t":"de","s":"H7497"},{"t":" ","s":null},{"t":"Bassan","s":"H154"},{"t":", un reste des Rephaïm, qui habitait à ","s":null},{"t":"Ashtaroth","s":"H3427"},{"t":" ","s":null},{"t":"et","s":"H6252"},{"t":" à Édréï:","s":null}],"text":"Et le territoire d'Og, roi de Bassan, un reste des Rephaïm, qui habitait à Ashtaroth et à Édréï:"},{"id":5,"segments":[{"t":"Il","s":"H4910"},{"t":" ","s":null},{"t":"dominait","s":"H1568"},{"t":" ","s":null},{"t":"sur","s":"H2022"},{"t":" ","s":null},{"t":"la","s":"H1651"},{"t":" ","s":null},{"t":"montagne","s":"H2768"},{"t":" ","s":null},{"t":"d'Hermon","s":"H5548"},{"t":", sur ","s":null},{"t":"Salca","s":"H3605"},{"t":", sur ","s":null},{"t":"tout","s":"H1316"},{"t":" ","s":null},{"t":"Bassan","s":"H5704"},{"t":" ","s":null},{"t":"jusqu'à","s":"H1366"},{"t":" la ","s":null},{"t":"frontière","s":"H5511"},{"t":" ","s":null},{"t":"des","s":"H2809"},{"t":" ","s":null},{"t":"Gueshuriens","s":"H2677"},{"t":" ","s":null},{"t":"et","s":"H4602"},{"t":" des Maacathiens, et sur la moitié de Galaad, frontière de Sihon, ","s":null},{"t":"roi","s":"H4428"},{"t":" de Hesbon.","s":null}],"text":"Il dominait sur la montagne d'Hermon, sur Salca, sur tout Bassan jusqu'à la frontière des Gueshuriens et des Maacathiens, et sur la moitié de Galaad, frontière de Sihon, roi de Hesbon."},{"id":6,"segments":[{"t":"Moïse","s":"H4872"},{"t":", ","s":null},{"t":"serviteur","s":"H5650"},{"t":" ","s":null},{"t":"de","s":"H3068"},{"t":" ","s":null},{"t":"l'Éternel","s":"H1121"},{"t":", ","s":null},{"t":"et","s":"H5414"},{"t":" ","s":null},{"t":"les","s":"H7206"},{"t":" ","s":null},{"t":"enfants","s":"H1425"},{"t":" ","s":null},{"t":"d'Israël","s":"H5221"},{"t":" les ","s":null},{"t":"battirent","s":"H3425"},{"t":"; et Moïse, serviteur de l'Éternel, en ","s":null},{"t":"donna","s":"H4519"},{"t":" la possession aux Rubénites, aux Gadites, et à la demi-tribu de Manassé.","s":null}],"text":"Moïse, serviteur de l'Éternel, et les enfants d'Israël les battirent; et Moïse, serviteur de l'Éternel, en donna la possession aux Rubénites, aux Gadites, et à la demi-tribu de Manassé."},{"id":7,"segments":[{"t":"Et","s":"H428"},{"t":" ","s":null},{"t":"voici","s":"H1121"},{"t":" ","s":null},{"t":"les","s":"H776"},{"t":" ","s":null},{"t":"rois","s":"H4428"},{"t":" ","s":null},{"t":"du","s":"H3383"},{"t":" ","s":null},{"t":"pays","s":"H3220"},{"t":", ","s":null},{"t":"que","s":"H1237"},{"t":" ","s":null},{"t":"Josué","s":"H3844"},{"t":" ","s":null},{"t":"et","s":"H834"},{"t":" les ","s":null},{"t":"enfants","s":"H3091"},{"t":" ","s":null},{"t":"d'Israël","s":"H4256"},{"t":" ","s":null},{"t":"battirent","s":"H7626"},{"t":" ","s":null},{"t":"de","s":"H5221"},{"t":" ","s":null},{"t":"ce","s":"H5676"},{"t":" ","s":null},{"t":"côté-ci","s":"H3478"},{"t":" du ","s":null},{"t":"Jourdain","s":"H5704"},{"t":", vers l'occident, ","s":null},{"t":"depuis","s":"H1171"},{"t":" Baal-Gad, dans ","s":null},{"t":"la","s":"H2510"},{"t":" vallée du Liban, ","s":null},{"t":"jusqu'à","s":"H2022"},{"t":" la ","s":null},{"t":"montagne","s":"H5927"},{"t":" nue ","s":null},{"t":"qui","s":"H8165"},{"t":" monte vers Séir, et dont Josué donna le pays en possession ","s":null},{"t":"aux","s":"H5414"},{"t":" ","s":null},{"t":"tribus","s":"H3425"},{"t":" d'Israël, selon leurs divisions,","s":null}],"text":"Et voici les rois du pays, que Josué et les enfants d'Israël battirent de ce côté-ci du Jourdain, vers l'occident, depuis Baal-Gad, dans la vallée du Liban, jusqu'à la montagne nue qui monte vers Séir, et dont Josué donna le pays en possession aux tribus d'Israël, selon leurs divisions,"},{"id":8,"segments":[{"t":"Dans","s":"H2022"},{"t":" ","s":null},{"t":"la","s":"H8219"},{"t":" ","s":null},{"t":"montagne","s":"H6160"},{"t":", ","s":null},{"t":"dans","s":"H794"},{"t":" la ","s":null},{"t":"plaine","s":"H4057"},{"t":", dans la ","s":null},{"t":"campagne","s":"H5045"},{"t":", ","s":null},{"t":"sur","s":"H2850"},{"t":" les coteaux, dans le désert, ","s":null},{"t":"et","s":"H2340"},{"t":" dans le midi, ","s":null},{"t":"pays","s":"H2983"},{"t":" ","s":null},{"t":"des","s":"H3669"},{"t":" Héthiens, des Amoréens, des Cananéens, des ","s":null},{"t":"Phéréziens","s":"H567"},{"t":", des ","s":null},{"t":"Héviens","s":"H6522"},{"t":" et des Jébusiens:","s":null}],"text":"Dans la montagne, dans la plaine, dans la campagne, sur les coteaux, dans le désert, et dans le midi, pays des Héthiens, des Amoréens, des Cananéens, des Phéréziens, des Héviens et des Jébusiens:"},{"id":9,"segments":[{"t":"Le","s":"H5857"},{"t":" ","s":null},{"t":"roi","s":"H4428"},{"t":" ","s":null},{"t":"de","s":"H3405"},{"t":" ","s":null},{"t":"Jérico","s":"H259"},{"t":", le roi d'Aï, qui ","s":null},{"t":"était","s":"H834"},{"t":" ","s":null},{"t":"à","s":"H6654"},{"t":" ","s":null},{"t":"côté","s":"H1008"},{"t":" de Béthel,","s":null}],"text":"Le roi de Jérico, le roi d'Aï, qui était à côté de Béthel,"},{"id":10,"segments":[{"t":"Le","s":"H2275"},{"t":" ","s":null},{"t":"roi","s":"H4428"},{"t":" ","s":null},{"t":"de","s":"H259"},{"t":" ","s":null},{"t":"Jérusalem","s":"H3389"},{"t":", le roi de Hébron,","s":null}],"text":"Le roi de Jérusalem, le roi de Hébron,"},{"id":11,"segments":[{"t":"Le","s":"H3412"},{"t":" ","s":null},{"t":"roi","s":"H4428"},{"t":" ","s":null},{"t":"de","s":"H3923"},{"t":" ","s":null},{"t":"Jarmuth","s":"H259"},{"t":", le roi de Lakis,","s":null}],"text":"Le roi de Jarmuth, le roi de Lakis,"},{"id":12,"segments":[{"t":"Le","s":"H5700"},{"t":" ","s":null},{"t":"roi","s":"H4428"},{"t":" ","s":null},{"t":"d'Églon","s":"H259"},{"t":", ","s":null},{"t":"le","s":"H1507"},{"t":" roi de Guézer,","s":null}],"text":"Le roi d'Églon, le roi de Guézer,"},{"id":13,"segments":[{"t":"Le","s":"H1688"},{"t":" ","s":null},{"t":"roi","s":"H4428"},{"t":" ","s":null},{"t":"de","s":"H1445"},{"t":" ","s":null},{"t":"Débir","s":"H259"},{"t":", le roi de Guéder,","s":null}],"text":"Le roi de Débir, le roi de Guéder,"},{"id":14,"segments":[{"t":"Le","s":"H2767"},{"t":" ","s":null},{"t":"roi","s":"H4428"},{"t":" ","s":null},{"t":"de","s":"H259"},{"t":" ","s":null},{"t":"Horma","s":"H6166"},{"t":", le roi d'Arad,","s":null}],"text":"Le roi de Horma, le roi d'Arad,"},{"id":15,"segments":[{"t":"Le","s":"H3841"},{"t":" ","s":null},{"t":"roi","s":"H4428"},{"t":" ","s":null},{"t":"de","s":"H259"},{"t":" ","s":null},{"t":"Libna","s":"H5725"},{"t":", le roi d'Adullam,","s":null}],"text":"Le roi de Libna, le roi d'Adullam,"},{"id":16,"segments":[{"t":"Le","s":"H4719"},{"t":" ","s":null},{"t":"roi","s":"H4428"},{"t":" ","s":null},{"t":"de","s":"H1008"},{"t":" ","s":null},{"t":"Makkéda","s":"H259"},{"t":", le roi de Béthel,","s":null}],"text":"Le roi de Makkéda, le roi de Béthel,"},{"id":17,"segments":[{"t":"Le","s":"H8599"},{"t":" ","s":null},{"t":"roi","s":"H4428"},{"t":" ","s":null},{"t":"de","s":"H2660"},{"t":" ","s":null},{"t":"Thappuach","s":"H259"},{"t":", le roi de Hépher,","s":null}],"text":"Le roi de Thappuach, le roi de Hépher,"},{"id":18,"segments":[{"t":"Le","s":"H663"},{"t":" ","s":null},{"t":"roi","s":"H4428"},{"t":" ","s":null},{"t":"d'Aphek","s":"H259"},{"t":", ","s":null},{"t":"le","s":"H8289"},{"t":" roi de Saron,","s":null}],"text":"Le roi d'Aphek, le roi de Saron,"},{"id":19,"segments":[{"t":"Le","s":"H4068"},{"t":" ","s":null},{"t":"roi","s":"H4428"},{"t":" ","s":null},{"t":"de","s":"H2674"},{"t":" ","s":null},{"t":"Madon","s":"H259"},{"t":", le roi de Hatsor,","s":null}],"text":"Le roi de Madon, le roi de Hatsor,"},{"id":20,"segments":[{"t":"Le","s":"H8112"},{"t":" ","s":null},{"t":"roi","s":"H4428"},{"t":" ","s":null},{"t":"de","s":"H259"},{"t":" ","s":null},{"t":"Shimron-Méron","s":"H407"},{"t":", le roi d'Acshaph,","s":null}],"text":"Le roi de Shimron-Méron, le roi d'Acshaph,"},{"id":21,"segments":[{"t":"Le","s":"H8590"},{"t":" ","s":null},{"t":"roi","s":"H4428"},{"t":" ","s":null},{"t":"de","s":"H4023"},{"t":" ","s":null},{"t":"Thaanac","s":"H259"},{"t":", le roi de Méguiddo,","s":null}],"text":"Le roi de Thaanac, le roi de Méguiddo,"},{"id":22,"segments":[{"t":"Le","s":"H3362"},{"t":" ","s":null},{"t":"roi","s":"H4428"},{"t":" ","s":null},{"t":"de","s":"H6943"},{"t":" ","s":null},{"t":"Kédès","s":"H259"},{"t":", le roi de ","s":null},{"t":"Joknéam","s":"H3760"},{"t":" du Carmel,","s":null}],"text":"Le roi de Kédès, le roi de Joknéam du Carmel,"},{"id":23,"segments":[{"t":"Le","s":"H1756"},{"t":" ","s":null},{"t":"roi","s":"H4428"},{"t":" ","s":null},{"t":"de","s":"H1471"},{"t":" ","s":null},{"t":"Dor","s":"H1537"},{"t":", sur ","s":null},{"t":"le","s":"H259"},{"t":"s hauteurs de Dor, le roi de Goïm, près de Guilgal,","s":null}],"text":"Le roi de Dor, sur les hauteurs de Dor, le roi de Goïm, près de Guilgal,"},{"id":24,"segments":[{"t":"Le ","s":null},{"t":"roi","s":"H4428"},{"t":" ","s":null},{"t":"de","s":"H8656"},{"t":" ","s":null},{"t":"Thirtsa","s":"H259"},{"t":"; ","s":null},{"t":"en","s":"H7970"},{"t":" tout trente et ","s":null},{"t":"un","s":"H3605"},{"t":" rois.","s":null}],"text":"Le roi de Thirtsa; en tout trente et un rois."}]},"es":{"verses":[{"id":1,"segments":[{"t":"ESTOS","s":"H428"},{"t":" ","s":null},{"t":"son","s":"H4217"},{"t":" ","s":null},{"t":"los","s":"H1121"},{"t":" ","s":null},{"t":"reyes","s":"H4428"},{"t":" ","s":null},{"t":"de","s":"H3383"},{"t":" ","s":null},{"t":"la","s":"H3423"},{"t":" ","s":null},{"t":"tierra","s":"H776"},{"t":" ","s":null},{"t":"que","s":"H769"},{"t":" los ","s":null},{"t":"hijos","s":"H6160"},{"t":" de Isra","s":null},{"t":"el","s":"H2768"},{"t":" ","s":null},{"t":"hirieron","s":"H5221"},{"t":", y ","s":null},{"t":"cuya","s":"H834"},{"t":" tierra poseyeron de la otra ","s":null},{"t":"parte","s":"H5676"},{"t":" del Jordán ","s":null},{"t":"al","s":"H5704"},{"t":" nacimiento del sol, desde el ","s":null},{"t":"arroyo","s":"H5158"},{"t":" de Arnón ","s":null},{"t":"hasta","s":"H2022"},{"t":" el ","s":null},{"t":"monte","s":"H3605"},{"t":" Hermón, y toda la llanura oriental:","s":null}],"text":"ESTOS son los reyes de la tierra que los hijos de Israel hirieron, y cuya tierra poseyeron de la otra parte del Jordán al nacimiento del sol, desde el arroyo de Arnón hasta el monte Hermón, y toda la llanura oriental:"},{"id":2,"segments":[{"t":"Sehón","s":"H5511"},{"t":" ","s":null},{"t":"rey","s":"H4428"},{"t":" ","s":null},{"t":"de","s":"H567"},{"t":" ","s":null},{"t":"los","s":"H8193"},{"t":" ","s":null},{"t":"Amorrheos","s":"H769"},{"t":", ","s":null},{"t":"que","s":"H3427"},{"t":" ","s":null},{"t":"habitaba","s":"H8432"},{"t":" ","s":null},{"t":"en","s":"H2809"},{"t":" ","s":null},{"t":"Hesbón","s":"H2999"},{"t":", y ","s":null},{"t":"señoreaba","s":"H1366"},{"t":" ","s":null},{"t":"desde","s":"H1121"},{"t":" ","s":null},{"t":"Aroer","s":"H6177"},{"t":", que ","s":null},{"t":"está","s":"H5921"},{"t":" á la ribera ","s":null},{"t":"del","s":"H5704"},{"t":" ","s":null},{"t":"arroyo","s":"H5158"},{"t":" de Arnón, y desde en medio del arroyo, y la mitad de Galaad, hasta el arroyo Jaboc, el ","s":null},{"t":"término","s":"H2677"},{"t":" de los hijos de Ammón;","s":null}],"text":"Sehón rey de los Amorrheos, que habitaba en Hesbón, y señoreaba desde Aroer, que está á la ribera del arroyo de Arnón, y desde en medio del arroyo, y la mitad de Galaad, hasta el arroyo Jaboc, el término de los hijos de Ammón;"},{"id":3,"segments":[{"t":"Y","s":"H6160"},{"t":" ","s":null},{"t":"de","s":"H5704"},{"t":"sde ","s":null},{"t":"la","s":"H3220"},{"t":" ","s":null},{"t":"campiña","s":"H794"},{"t":" ","s":null},{"t":"hasta","s":"H4217"},{"t":" la ","s":null},{"t":"mar","s":"H3672"},{"t":" de ","s":null},{"t":"Cinneroth","s":"H6449"},{"t":", al oriente; y hasta la mar de la llanura, ","s":null},{"t":"el","s":"H1870"},{"t":" mar Salado, al oriente, por el camino de Beth-jesimoth; y desde el ","s":null},{"t":"mediodía","s":"H8486"},{"t":" ","s":null},{"t":"debajo","s":"H8478"},{"t":" de las vertientes del Pisga.","s":null}],"text":"Y desde la campiña hasta la mar de Cinneroth, al oriente; y hasta la mar de la llanura, el mar Salado, al oriente, por el camino de Beth-jesimoth; y desde el mediodía debajo de las vertientes del Pisga."},{"id":4,"segments":[{"t":"Y","s":"H1366"},{"t":" ","s":null},{"t":"los","s":"H5747"},{"t":" ","s":null},{"t":"términos","s":"H4428"},{"t":" ","s":null},{"t":"de","s":"H1316"},{"t":" ","s":null},{"t":"Og","s":"H3499"},{"t":" ","s":null},{"t":"rey","s":"H7497"},{"t":" de ","s":null},{"t":"Basán","s":"H154"},{"t":", que había quedado de los Rapheos, el cual habitaba ","s":null},{"t":"en","s":"H3427"},{"t":" ","s":null},{"t":"Astaroth","s":"H6252"},{"t":" y en Edrei,","s":null}],"text":"Y los términos de Og rey de Basán, que había quedado de los Rapheos, el cual habitaba en Astaroth y en Edrei,"},{"id":5,"segments":[{"t":"Y","s":"H4910"},{"t":" ","s":null},{"t":"señoreaba","s":"H1568"},{"t":" ","s":null},{"t":"en","s":"H2022"},{"t":" ","s":null},{"t":"el","s":"H1651"},{"t":" ","s":null},{"t":"monte","s":"H2768"},{"t":" ","s":null},{"t":"de","s":"H5548"},{"t":" ","s":null},{"t":"Hermón","s":"H3605"},{"t":", ","s":null},{"t":"y","s":"H1316"},{"t":" en ","s":null},{"t":"Salca","s":"H5704"},{"t":", y en ","s":null},{"t":"todo","s":"H1366"},{"t":" ","s":null},{"t":"Basán","s":"H5511"},{"t":" ","s":null},{"t":"hasta","s":"H2809"},{"t":" los ","s":null},{"t":"términos","s":"H4602"},{"t":" de ","s":null},{"t":"Gessuri","s":"H2677"},{"t":" y de Maachâti, y la mitad de Galaad, término de ","s":null},{"t":"Sehón","s":"H4428"},{"t":" rey de Hesbón.","s":null}],"text":"Y señoreaba en el monte de Hermón, y en Salca, y en todo Basán hasta los términos de Gessuri y de Maachâti, y la mitad de Galaad, término de Sehón rey de Hesbón."},{"id":6,"segments":[{"t":"A","s":"H4872"},{"t":" ","s":null},{"t":"estos","s":"H5650"},{"t":" ","s":null},{"t":"hirieron","s":"H3068"},{"t":" ","s":null},{"t":"Moisés","s":"H1121"},{"t":" ","s":null},{"t":"siervo","s":"H3425"},{"t":" ","s":null},{"t":"de","s":"H7206"},{"t":" ","s":null},{"t":"Jehová","s":"H1425"},{"t":" ","s":null},{"t":"y","s":"H5414"},{"t":" ","s":null},{"t":"los","s":"H5221"},{"t":" ","s":null},{"t":"hijos","s":"H2677"},{"t":" de ","s":null},{"t":"Israel","s":"H4519"},{"t":"; y Moisés siervo de Jehová dió aquella ","s":null},{"t":"tierra","s":"H776"},{"t":" en posesión á los Rubenitas, Gaditas, y á la media tribu de Manasés.","s":null}],"text":"A estos hirieron Moisés siervo de Jehová y los hijos de Israel; y Moisés siervo de Jehová dió aquella tierra en posesión á los Rubenitas, Gaditas, y á la media tribu de Manasés."},{"id":7,"segments":[{"t":"Y","s":"H428"},{"t":" ","s":null},{"t":"estos","s":"H1121"},{"t":" ","s":null},{"t":"son","s":"H3383"},{"t":" ","s":null},{"t":"los","s":"H4428"},{"t":" ","s":null},{"t":"reyes","s":"H3220"},{"t":" ","s":null},{"t":"de","s":"H5221"},{"t":" ","s":null},{"t":"la","s":"H1237"},{"t":" ","s":null},{"t":"tierra","s":"H776"},{"t":" ","s":null},{"t":"que","s":"H3844"},{"t":" ","s":null},{"t":"hirió","s":"H834"},{"t":" ","s":null},{"t":"Josué","s":"H3091"},{"t":" ","s":null},{"t":"con","s":"H4256"},{"t":" los ","s":null},{"t":"hijos","s":"H7626"},{"t":" de ","s":null},{"t":"Israel","s":"H5676"},{"t":", de ","s":null},{"t":"esta","s":"H3478"},{"t":" parte ","s":null},{"t":"del","s":"H5704"},{"t":" Jordán al ","s":null},{"t":"occidente","s":"H1171"},{"t":", desde Baal-gad en el llano del Líbano hasta el ","s":null},{"t":"monte","s":"H2510"},{"t":" de ","s":null},{"t":"Halac","s":"H5927"},{"t":" que ","s":null},{"t":"sube","s":"H8165"},{"t":" á Seir; la cual tierra dió Josué en posesión á las ","s":null},{"t":"tribus","s":"H5414"},{"t":" de Israel, ","s":null},{"t":"conforme","s":"H3425"},{"t":" á sus repartimientos;","s":null}],"text":"Y estos son los reyes de la tierra que hirió Josué con los hijos de Israel, de esta parte del Jordán al occidente, desde Baal-gad en el llano del Líbano hasta el monte de Halac que sube á Seir; la cual tierra dió Josué en posesión á las tribus de Israel, conforme á sus repartimientos;"},{"id":8,"segments":[{"t":"En","s":"H2022"},{"t":" ","s":null},{"t":"montes","s":"H8219"},{"t":" ","s":null},{"t":"y","s":"H6160"},{"t":" ","s":null},{"t":"en","s":"H794"},{"t":" ","s":null},{"t":"valles","s":"H4057"},{"t":", en ","s":null},{"t":"llanos","s":"H5045"},{"t":" y en ","s":null},{"t":"vertientes","s":"H2850"},{"t":", al desierto y al mediodía; ","s":null},{"t":"el","s":"H3669"},{"t":" Hetheo, y el ","s":null},{"t":"Amorrheo","s":"H2983"},{"t":", y el Cananeo, y el ","s":null},{"t":"Pherezeo","s":"H567"},{"t":", y el ","s":null},{"t":"Heveo","s":"H6522"},{"t":", y el ","s":null},{"t":"Jebuseo","s":"H2340"},{"t":".","s":null}],"text":"En montes y en valles, en llanos y en vertientes, al desierto y al mediodía; el Hetheo, y el Amorrheo, y el Cananeo, y el Pherezeo, y el Heveo, y el Jebuseo."},{"id":9,"segments":[{"t":"El","s":"H4428"},{"t":" ","s":null},{"t":"rey","s":"H5857"},{"t":" ","s":null},{"t":"de","s":"H3405"},{"t":" Jericó, ","s":null},{"t":"uno","s":"H259"},{"t":": el rey de Hai, que ","s":null},{"t":"está","s":"H834"},{"t":" al ","s":null},{"t":"lado","s":"H6654"},{"t":" de ","s":null},{"t":"Beth-el","s":"H1008"},{"t":", otro:","s":null}],"text":"El rey de Jericó, uno: el rey de Hai, que está al lado de Beth-el, otro:"},{"id":10,"segments":[{"t":"El","s":"H4428"},{"t":" ","s":null},{"t":"rey","s":"H2275"},{"t":" ","s":null},{"t":"de","s":"H3389"},{"t":" Jerusalem, ","s":null},{"t":"otro","s":"H259"},{"t":": el rey de Hebrón, otro:","s":null}],"text":"El rey de Jerusalem, otro: el rey de Hebrón, otro:"},{"id":11,"segments":[{"t":"El","s":"H4428"},{"t":" ","s":null},{"t":"rey","s":"H3923"},{"t":" ","s":null},{"t":"de","s":"H3412"},{"t":" Jarmuth, ","s":null},{"t":"otro","s":"H259"},{"t":": el rey de Lachîs, otro:","s":null}],"text":"El rey de Jarmuth, otro: el rey de Lachîs, otro:"},{"id":12,"segments":[{"t":"El","s":"H4428"},{"t":" ","s":null},{"t":"rey","s":"H1507"},{"t":" ","s":null},{"t":"de","s":"H5700"},{"t":" Eglón, ","s":null},{"t":"otro","s":"H259"},{"t":": el rey de Gezer, otro:","s":null}],"text":"El rey de Eglón, otro: el rey de Gezer, otro:"},{"id":13,"segments":[{"t":"El","s":"H4428"},{"t":" ","s":null},{"t":"rey","s":"H1445"},{"t":" ","s":null},{"t":"de","s":"H1688"},{"t":" Debir, ","s":null},{"t":"otro","s":"H259"},{"t":": el rey de Geder, otro:","s":null}],"text":"El rey de Debir, otro: el rey de Geder, otro:"},{"id":14,"segments":[{"t":"El","s":"H4428"},{"t":" ","s":null},{"t":"rey","s":"H6166"},{"t":" ","s":null},{"t":"de","s":"H2767"},{"t":" Horma, ","s":null},{"t":"otro","s":"H259"},{"t":": el rey de Arad, otro:","s":null}],"text":"El rey de Horma, otro: el rey de Arad, otro:"},{"id":15,"segments":[{"t":"El","s":"H4428"},{"t":" ","s":null},{"t":"rey","s":"H5725"},{"t":" ","s":null},{"t":"de","s":"H3841"},{"t":" Libna, ","s":null},{"t":"otro","s":"H259"},{"t":": el rey de Adullam, otro:","s":null}],"text":"El rey de Libna, otro: el rey de Adullam, otro:"},{"id":16,"segments":[{"t":"El","s":"H4428"},{"t":" ","s":null},{"t":"rey","s":"H1008"},{"t":" ","s":null},{"t":"de","s":"H4719"},{"t":" Maceda, ","s":null},{"t":"otro","s":"H259"},{"t":": el rey de Beth-el, otro:","s":null}],"text":"El rey de Maceda, otro: el rey de Beth-el, otro:"},{"id":17,"segments":[{"t":"El","s":"H4428"},{"t":" ","s":null},{"t":"rey","s":"H2660"},{"t":" ","s":null},{"t":"de","s":"H8599"},{"t":" Tappua, ","s":null},{"t":"otro","s":"H259"},{"t":": el rey de Hepher, otro:","s":null}],"text":"El rey de Tappua, otro: el rey de Hepher, otro:"},{"id":18,"segments":[{"t":"El","s":"H4428"},{"t":" ","s":null},{"t":"rey","s":"H8289"},{"t":" ","s":null},{"t":"de","s":"H663"},{"t":" Aphec, ","s":null},{"t":"otro","s":"H259"},{"t":": el rey de Lasarón, otro:","s":null}],"text":"El rey de Aphec, otro: el rey de Lasarón, otro:"},{"id":19,"segments":[{"t":"El","s":"H4428"},{"t":" ","s":null},{"t":"rey","s":"H2674"},{"t":" ","s":null},{"t":"de","s":"H4068"},{"t":" Madón, ","s":null},{"t":"otro","s":"H259"},{"t":": el rey de Hasor, otro:","s":null}],"text":"El rey de Madón, otro: el rey de Hasor, otro:"},{"id":20,"segments":[{"t":"El","s":"H4428"},{"t":" ","s":null},{"t":"rey","s":"H407"},{"t":" ","s":null},{"t":"de","s":"H8112"},{"t":" Simrom-meron, ","s":null},{"t":"otro","s":"H259"},{"t":": el rey de Achsaph, otro:","s":null}],"text":"El rey de Simrom-meron, otro: el rey de Achsaph, otro:"},{"id":21,"segments":[{"t":"El","s":"H4428"},{"t":" ","s":null},{"t":"rey","s":"H4023"},{"t":" ","s":null},{"t":"de","s":"H8590"},{"t":" Taanach, ","s":null},{"t":"otro","s":"H259"},{"t":": el rey de Megiddo, otro:","s":null}],"text":"El rey de Taanach, otro: el rey de Megiddo, otro:"},{"id":22,"segments":[{"t":"El","s":"H4428"},{"t":" ","s":null},{"t":"rey","s":"H3362"},{"t":" ","s":null},{"t":"de","s":"H6943"},{"t":" Chêdes, ","s":null},{"t":"otro","s":"H259"},{"t":": el rey de ","s":null},{"t":"Jocneam","s":"H3760"},{"t":" de Carmel, otro:","s":null}],"text":"El rey de Chêdes, otro: el rey de Jocneam de Carmel, otro:"},{"id":23,"segments":[{"t":"El","s":"H4428"},{"t":" ","s":null},{"t":"rey","s":"H1756"},{"t":" ","s":null},{"t":"de","s":"H1471"},{"t":" ","s":null},{"t":"Dor","s":"H1537"},{"t":", de la provincia de Dor, otro; ","s":null},{"t":"el","s":"H259"},{"t":" rey de Gentes en Gilgal, otro:","s":null}],"text":"El rey de Dor, de la provincia de Dor, otro; el rey de Gentes en Gilgal, otro:"},{"id":24,"segments":[{"t":"El","s":"H4428"},{"t":" rey ","s":null},{"t":"de","s":"H8656"},{"t":" Tirsa, ","s":null},{"t":"otro","s":"H259"},{"t":": ","s":null},{"t":"treinta","s":"H7970"},{"t":" y un ","s":null},{"t":"reyes","s":"H3605"},{"t":" en todo.","s":null}],"text":"El rey de Tirsa, otro: treinta y un reyes en todo."}]},"nl":{"verses":[{"id":1,"segments":[{"t":"Dit","s":"H428"},{"t":" ","s":null},{"t":"nu","s":"H769"},{"t":" ","s":null},{"t":"zijn","s":"H3383"},{"t":" ","s":null},{"t":"de","s":"H776"},{"t":" ","s":null},{"t":"koningen","s":"H4428"},{"t":" ","s":null},{"t":"des","s":"H1121"},{"t":" ","s":null},{"t":"lands","s":"H4217"},{"t":", ","s":null},{"t":"die","s":"H6160"},{"t":" de kinderen Israels geslagen hebben, en ","s":null},{"t":"hun","s":"H5221"},{"t":" land ","s":null},{"t":"erfelijk","s":"H834"},{"t":" bezaten, aan gene ","s":null},{"t":"zijde","s":"H3423"},{"t":" van de ","s":null},{"t":"Jordaan","s":"H5676"},{"t":", tegen den ","s":null},{"t":"opgang","s":"H5704"},{"t":" der zon; van de beek Arnon af ","s":null},{"t":"tot","s":"H5158"},{"t":" den ","s":null},{"t":"berg","s":"H2022"},{"t":" Hermon, en ","s":null},{"t":"het","s":"H3605"},{"t":" ganse vlakke veld tegen het oosten:","s":null}],"text":"Dit nu zijn de koningen des lands, die de kinderen Israels geslagen hebben, en hun land erfelijk bezaten, aan gene zijde van de Jordaan, tegen den opgang der zon; van de beek Arnon af tot den berg Hermon, en het ganse vlakke veld tegen het oosten:"},{"id":2,"segments":[{"t":"Sihon","s":"H5511"},{"t":", ","s":null},{"t":"de","s":"H4428"},{"t":" ","s":null},{"t":"koning","s":"H567"},{"t":" ","s":null},{"t":"der","s":"H8193"},{"t":" ","s":null},{"t":"Amorieten","s":"H769"},{"t":", ","s":null},{"t":"die","s":"H3427"},{"t":" te ","s":null},{"t":"Hesbon","s":"H2809"},{"t":" ","s":null},{"t":"woonde","s":"H4910"},{"t":"; die ","s":null},{"t":"van","s":"H2999"},{"t":" ","s":null},{"t":"Aroer","s":"H1366"},{"t":" ","s":null},{"t":"af","s":"H6177"},{"t":" ","s":null},{"t":"heerste","s":"H1121"},{"t":", ","s":null},{"t":"welke","s":"H5921"},{"t":" ","s":null},{"t":"aan","s":"H1568"},{"t":" den oever der ","s":null},{"t":"beek","s":"H5704"},{"t":" ","s":null},{"t":"Arnon","s":"H5158"},{"t":" is, en over het midden der beek en de helft van Gilead, en tot aan de beek ","s":null},{"t":"Jabbok","s":"H5983"},{"t":", de ","s":null},{"t":"landpale","s":"H2677"},{"t":" der kinderen Ammons;","s":null}],"text":"Sihon, de koning der Amorieten, die te Hesbon woonde; die van Aroer af heerste, welke aan den oever der beek Arnon is, en over het midden der beek en de helft van Gilead, en tot aan de beek Jabbok, de landpale der kinderen Ammons;"},{"id":3,"segments":[{"t":"En","s":"H6160"},{"t":" ","s":null},{"t":"over","s":"H794"},{"t":" ","s":null},{"t":"het","s":"H3220"},{"t":" ","s":null},{"t":"vlakke","s":"H6449"},{"t":" ","s":null},{"t":"veld","s":"H4217"},{"t":" ","s":null},{"t":"tot","s":"H3672"},{"t":" ","s":null},{"t":"aan","s":"H5704"},{"t":" de zee ","s":null},{"t":"van","s":"H8478"},{"t":" Cinneroth tegen het oosten, en tot aan de zee des vlakken velds, de Zoutzee, tegen het oosten, op den ","s":null},{"t":"weg","s":"H1020"},{"t":" ","s":null},{"t":"naar","s":"H1870"},{"t":" ","s":null},{"t":"Beth-Jesimoth","s":"H8486"},{"t":"; en van het zuiden beneden Asdoth-Pisga.","s":null}],"text":"En over het vlakke veld tot aan de zee van Cinneroth tegen het oosten, en tot aan de zee des vlakken velds, de Zoutzee, tegen het oosten, op den weg naar Beth-Jesimoth; en van het zuiden beneden Asdoth-Pisga."},{"id":4,"segments":[{"t":"Daartoe","s":"H1366"},{"t":" ","s":null},{"t":"de","s":"H5747"},{"t":" ","s":null},{"t":"landpale","s":"H4428"},{"t":" ","s":null},{"t":"van","s":"H1316"},{"t":" ","s":null},{"t":"Og","s":"H3499"},{"t":", ","s":null},{"t":"den","s":"H7497"},{"t":" ","s":null},{"t":"koning","s":"H154"},{"t":" van Bazan, die van het overblijfsel der reuzen was, wonende ","s":null},{"t":"te","s":"H3427"},{"t":" ","s":null},{"t":"Astharoth","s":"H6252"},{"t":" en te Edrei.","s":null}],"text":"Daartoe de landpale van Og, den koning van Bazan, die van het overblijfsel der reuzen was, wonende te Astharoth en te Edrei."},{"id":5,"segments":[{"t":"En","s":"H4910"},{"t":" ","s":null},{"t":"heerste","s":"H2809"},{"t":" ","s":null},{"t":"over","s":"H2022"},{"t":" ","s":null},{"t":"den","s":"H1568"},{"t":" ","s":null},{"t":"berg","s":"H1651"},{"t":" ","s":null},{"t":"Hermon","s":"H2768"},{"t":", en over ","s":null},{"t":"Salcha","s":"H3605"},{"t":", en over ","s":null},{"t":"geheel","s":"H1316"},{"t":" ","s":null},{"t":"Bazan","s":"H5704"},{"t":", ","s":null},{"t":"tot","s":"H1366"},{"t":" ","s":null},{"t":"aan","s":"H5511"},{"t":" de landpale ","s":null},{"t":"der","s":"H2677"},{"t":" ","s":null},{"t":"Gezurieten","s":"H4602"},{"t":", en der Maachathieten; en de helft van Gilead, de landpale van ","s":null},{"t":"Sihon","s":"H4428"},{"t":", den koning van Hesbon.","s":null}],"text":"En heerste over den berg Hermon, en over Salcha, en over geheel Bazan, tot aan de landpale der Gezurieten, en der Maachathieten; en de helft van Gilead, de landpale van Sihon, den koning van Hesbon."},{"id":6,"segments":[{"t":"Mozes","s":"H4872"},{"t":", ","s":null},{"t":"de","s":"H5650"},{"t":" ","s":null},{"t":"knecht","s":"H3068"},{"t":" ","s":null},{"t":"des","s":"H1121"},{"t":" ","s":null},{"t":"HEEREN","s":"H5414"},{"t":", ","s":null},{"t":"en","s":"H7206"},{"t":" de ","s":null},{"t":"kinderen","s":"H1425"},{"t":" ","s":null},{"t":"Israels","s":"H2677"},{"t":" ","s":null},{"t":"sloegen","s":"H5221"},{"t":" ","s":null},{"t":"hen","s":"H4519"},{"t":", en Mozes, de knecht des HEEREN, ","s":null},{"t":"gaf","s":"H3425"},{"t":" aan de Rubenieten en aan de Gadieten, en aan den halven stam van Manasse, dat land tot een erfelijke bezitting.","s":null}],"text":"Mozes, de knecht des HEEREN, en de kinderen Israels sloegen hen, en Mozes, de knecht des HEEREN, gaf aan de Rubenieten en aan de Gadieten, en aan den halven stam van Manasse, dat land tot een erfelijke bezitting."},{"id":7,"segments":[{"t":"Dit","s":"H428"},{"t":" ","s":null},{"t":"nu","s":"H1121"},{"t":" ","s":null},{"t":"zijn","s":"H776"},{"t":" ","s":null},{"t":"de","s":"H4428"},{"t":" ","s":null},{"t":"koningen","s":"H3383"},{"t":" ","s":null},{"t":"des","s":"H3220"},{"t":" ","s":null},{"t":"lands","s":"H1237"},{"t":", ","s":null},{"t":"die","s":"H3844"},{"t":" ","s":null},{"t":"Jozua","s":"H4256"},{"t":" ","s":null},{"t":"sloeg","s":"H834"},{"t":", en de ","s":null},{"t":"kinderen","s":"H7626"},{"t":" ","s":null},{"t":"Israels","s":"H3478"},{"t":", ","s":null},{"t":"aan","s":"H5927"},{"t":" ","s":null},{"t":"deze","s":"H5221"},{"t":" ","s":null},{"t":"zijde","s":"H5676"},{"t":" ","s":null},{"t":"van","s":"H1171"},{"t":" de ","s":null},{"t":"Jordaan","s":"H5704"},{"t":" tegen het westen, van Baal-Gad aan, in het dal van den ","s":null},{"t":"Libanon","s":"H2022"},{"t":", en ","s":null},{"t":"tot","s":"H2510"},{"t":" aan den kalen ","s":null},{"t":"berg","s":"H8165"},{"t":", die naar Seir opgaat; en Jozua gaf het aan de stammen Israels tot ","s":null},{"t":"een","s":"H5414"},{"t":" erfelijke ","s":null},{"t":"bezitting","s":"H3425"},{"t":", naar hun afdelingen.","s":null}],"text":"Dit nu zijn de koningen des lands, die Jozua sloeg, en de kinderen Israels, aan deze zijde van de Jordaan tegen het westen, van Baal-Gad aan, in het dal van den Libanon, en tot aan den kalen berg, die naar Seir opgaat; en Jozua gaf het aan de stammen Israels tot een erfelijke bezitting, naar hun afdelingen."},{"id":8,"segments":[{"t":"Wat","s":"H2022"},{"t":" ","s":null},{"t":"op","s":"H8219"},{"t":" ","s":null},{"t":"het","s":"H6160"},{"t":" ","s":null},{"t":"gebergte","s":"H794"},{"t":", ","s":null},{"t":"en","s":"H4057"},{"t":" ","s":null},{"t":"in","s":"H5045"},{"t":" ","s":null},{"t":"de","s":"H2850"},{"t":" laagte, en in het vlakke veld, en in de aflopingen der ","s":null},{"t":"wateren","s":"H4325"},{"t":", en in de woestijn, en ","s":null},{"t":"tegen","s":"H2983"},{"t":" het zuiden was: de Hethieten, de Amorieten, en ","s":null},{"t":"Kanaanieten","s":"H567"},{"t":", de ","s":null},{"t":"Ferezieten","s":"H3669"},{"t":", de ","s":null},{"t":"Hevieten","s":"H6522"},{"t":", en de ","s":null},{"t":"Jebusieten","s":"H2340"},{"t":".","s":null}],"text":"Wat op het gebergte, en in de laagte, en in het vlakke veld, en in de aflopingen der wateren, en in de woestijn, en tegen het zuiden was: de Hethieten, de Amorieten, en Kanaanieten, de Ferezieten, de Hevieten, en de Jebusieten."},{"id":9,"segments":[{"t":"De","s":"H4428"},{"t":" ","s":null},{"t":"koning","s":"H5857"},{"t":" ","s":null},{"t":"van","s":"H3405"},{"t":" Jericho, ","s":null},{"t":"een","s":"H259"},{"t":"; de koning van Ai, die ","s":null},{"t":"ter","s":"H834"},{"t":" ","s":null},{"t":"zijde","s":"H6654"},{"t":" van ","s":null},{"t":"Beth-El","s":"H1008"},{"t":" is, een;","s":null}],"text":"De koning van Jericho, een; de koning van Ai, die ter zijde van Beth-El is, een;"},{"id":10,"segments":[{"t":"De","s":"H4428"},{"t":" ","s":null},{"t":"koning","s":"H2275"},{"t":" ","s":null},{"t":"van","s":"H3389"},{"t":" Jeruzalem, ","s":null},{"t":"een","s":"H259"},{"t":"; de koning van Hebron, een;","s":null}],"text":"De koning van Jeruzalem, een; de koning van Hebron, een;"},{"id":11,"segments":[{"t":"De","s":"H4428"},{"t":" ","s":null},{"t":"koning","s":"H3923"},{"t":" ","s":null},{"t":"van","s":"H3412"},{"t":" Jarmuth, ","s":null},{"t":"een","s":"H259"},{"t":"; de koning van Lachis, een;","s":null}],"text":"De koning van Jarmuth, een; de koning van Lachis, een;"},{"id":12,"segments":[{"t":"De","s":"H4428"},{"t":" ","s":null},{"t":"koning","s":"H1507"},{"t":" ","s":null},{"t":"van","s":"H5700"},{"t":" ","s":null},{"t":"Eglon","s":"H259"},{"t":", een; de koning Gezer, een;","s":null}],"text":"De koning van Eglon, een; de koning Gezer, een;"},{"id":13,"segments":[{"t":"De","s":"H4428"},{"t":" ","s":null},{"t":"koning","s":"H1445"},{"t":" ","s":null},{"t":"van","s":"H1688"},{"t":" Debir, ","s":null},{"t":"een","s":"H259"},{"t":"; de koning van Geder, een;","s":null}],"text":"De koning van Debir, een; de koning van Geder, een;"},{"id":14,"segments":[{"t":"De","s":"H4428"},{"t":" ","s":null},{"t":"koning","s":"H6166"},{"t":" ","s":null},{"t":"van","s":"H2767"},{"t":" Horma, ","s":null},{"t":"een","s":"H259"},{"t":"; de koning van Harad, een;","s":null}],"text":"De koning van Horma, een; de koning van Harad, een;"},{"id":15,"segments":[{"t":"De","s":"H4428"},{"t":" ","s":null},{"t":"koning","s":"H5725"},{"t":" ","s":null},{"t":"van","s":"H3841"},{"t":" Libna, ","s":null},{"t":"een","s":"H259"},{"t":"; de koning van Adullam, een;","s":null}],"text":"De koning van Libna, een; de koning van Adullam, een;"},{"id":16,"segments":[{"t":"De","s":"H4428"},{"t":" ","s":null},{"t":"koning","s":"H1008"},{"t":" ","s":null},{"t":"van","s":"H4719"},{"t":" Makkeda, ","s":null},{"t":"een","s":"H259"},{"t":"; de koning van Beth-El, een;","s":null}],"text":"De koning van Makkeda, een; de koning van Beth-El, een;"},{"id":17,"segments":[{"t":"De","s":"H4428"},{"t":" ","s":null},{"t":"koning","s":"H2660"},{"t":" ","s":null},{"t":"van","s":"H8599"},{"t":" Tappuah, ","s":null},{"t":"een","s":"H259"},{"t":"; de koning van Hefer, een;","s":null}],"text":"De koning van Tappuah, een; de koning van Hefer, een;"},{"id":18,"segments":[{"t":"De","s":"H4428"},{"t":" ","s":null},{"t":"koning","s":"H8289"},{"t":" ","s":null},{"t":"van","s":"H663"},{"t":" Afek, ","s":null},{"t":"een","s":"H259"},{"t":"; de koning van Lassaron, een;","s":null}],"text":"De koning van Afek, een; de koning van Lassaron, een;"},{"id":19,"segments":[{"t":"De","s":"H4428"},{"t":" ","s":null},{"t":"koning","s":"H2674"},{"t":" ","s":null},{"t":"van","s":"H4068"},{"t":" Madon, ","s":null},{"t":"een","s":"H259"},{"t":"; de koning van Hazor, een;","s":null}],"text":"De koning van Madon, een; de koning van Hazor, een;"},{"id":20,"segments":[{"t":"De","s":"H4428"},{"t":" ","s":null},{"t":"koning","s":"H407"},{"t":" ","s":null},{"t":"van","s":"H8112"},{"t":" Simron-Meron, ","s":null},{"t":"een","s":"H259"},{"t":"; de koning van Achsaf, een;","s":null}],"text":"De koning van Simron-Meron, een; de koning van Achsaf, een;"},{"id":21,"segments":[{"t":"De","s":"H4428"},{"t":" ","s":null},{"t":"koning","s":"H4023"},{"t":" ","s":null},{"t":"van","s":"H8590"},{"t":" Taanach, ","s":null},{"t":"een","s":"H259"},{"t":"; de koning van Megiddo, een;","s":null}],"text":"De koning van Taanach, een; de koning van Megiddo, een;"},{"id":22,"segments":[{"t":"De","s":"H4428"},{"t":" ","s":null},{"t":"koning","s":"H3362"},{"t":" ","s":null},{"t":"van","s":"H6943"},{"t":" Kedes, ","s":null},{"t":"een","s":"H259"},{"t":"; de koning van Jokneam, ","s":null},{"t":"aan","s":"H3760"},{"t":" den Karmel, een;","s":null}],"text":"De koning van Kedes, een; de koning van Jokneam, aan den Karmel, een;"},{"id":23,"segments":[{"t":"De","s":"H4428"},{"t":" ","s":null},{"t":"koning","s":"H1756"},{"t":" ","s":null},{"t":"van","s":"H1471"},{"t":" ","s":null},{"t":"Dor","s":"H1537"},{"t":", tot Nafath-Dor, een; ","s":null},{"t":"de","s":"H259"},{"t":" koning der heidenen te Gilgal, een;","s":null}],"text":"De koning van Dor, tot Nafath-Dor, een; de koning der heidenen te Gilgal, een;"},{"id":24,"segments":[{"t":"De","s":"H4428"},{"t":" koning van ","s":null},{"t":"Thirza","s":"H8656"},{"t":", ","s":null},{"t":"een","s":"H259"},{"t":". ","s":null},{"t":"Al","s":"H7970"},{"t":" deze koningen ","s":null},{"t":"zijn","s":"H3605"},{"t":" een en dertig.","s":null}],"text":"De koning van Thirza, een. Al deze koningen zijn een en dertig."}]},"pt":{"verses":[{"id":1,"segments":[{"t":"São","s":"H428"},{"t":" ","s":null},{"t":"estes","s":"H3383"},{"t":" ","s":null},{"t":"os","s":"H776"},{"t":" ","s":null},{"t":"reis","s":"H4428"},{"t":" ","s":null},{"t":"que","s":"H1121"},{"t":" os ","s":null},{"t":"israelitas","s":"H4217"},{"t":" ","s":null},{"t":"derrotaram","s":"H769"},{"t":", e de ","s":null},{"t":"cujo","s":"H5221"},{"t":" território ","s":null},{"t":"se","s":"H834"},{"t":" apossaram a ","s":null},{"t":"leste","s":"H3423"},{"t":" do ","s":null},{"t":"Jordão","s":"H5676"},{"t":", desde o ribeiro do Arnom até o ","s":null},{"t":"monte","s":"H5158"},{"t":" ","s":null},{"t":"Hermom","s":"H3605"},{"t":", ","s":null},{"t":"inclusive","s":"H2022"},{"t":" ","s":null},{"t":"todo","s":"H2768"},{"t":" o lado leste da Arabá:","s":null}],"text":"São estes os reis que os israelitas derrotaram, e de cujo território se apossaram a leste do Jordão, desde o ribeiro do Arnom até o monte Hermom, inclusive todo o lado leste da Arabá:"},{"id":2,"segments":[{"t":"Seom","s":"H5511"},{"t":", ","s":null},{"t":"rei","s":"H4428"},{"t":" ","s":null},{"t":"dos","s":"H567"},{"t":" ","s":null},{"t":"amorreus","s":"H8193"},{"t":", ","s":null},{"t":"que","s":"H769"},{"t":" ","s":null},{"t":"reinou","s":"H3427"},{"t":" ","s":null},{"t":"em","s":"H2809"},{"t":" ","s":null},{"t":"Hesbom","s":"H8432"},{"t":". ","s":null},{"t":"Governou","s":"H4910"},{"t":" ","s":null},{"t":"desde","s":"H2999"},{"t":" ","s":null},{"t":"Aroer","s":"H6177"},{"t":", ","s":null},{"t":"na","s":"H1366"},{"t":" ","s":null},{"t":"borda","s":"H5921"},{"t":" do ","s":null},{"t":"ribeiro","s":"H1568"},{"t":" do Arnom, desde o meio do ribeiro, até o ","s":null},{"t":"rio","s":"H5704"},{"t":" Jaboque, que é a fronteira dos amonitas. ","s":null},{"t":"Esse","s":"H5983"},{"t":" ","s":null},{"t":"território","s":"H2677"},{"t":" incluía a metade de Gileade.","s":null}],"text":"Seom, rei dos amorreus, que reinou em Hesbom. Governou desde Aroer, na borda do ribeiro do Arnom, desde o meio do ribeiro, até o rio Jaboque, que é a fronteira dos amonitas. Esse território incluía a metade de Gileade."},{"id":3,"segments":[{"t":"Também","s":"H6160"},{"t":" ","s":null},{"t":"governou","s":"H794"},{"t":" a ","s":null},{"t":"Arabá","s":"H4217"},{"t":" ","s":null},{"t":"oriental","s":"H3672"},{"t":", ","s":null},{"t":"desde","s":"H6449"},{"t":" o ","s":null},{"t":"mar","s":"H5704"},{"t":" de Quinerete até o mar da Arabá, o mar Salgado, até Bete-Jesimote, e mais ","s":null},{"t":"ao","s":"H1020"},{"t":" ","s":null},{"t":"sul","s":"H1870"},{"t":", ao ","s":null},{"t":"pé","s":"H8486"},{"t":" ","s":null},{"t":"das","s":"H8478"},{"t":" encostas do Pisga.","s":null}],"text":"Também governou a Arabá oriental, desde o mar de Quinerete até o mar da Arabá, o mar Salgado, até Bete-Jesimote, e mais ao sul, ao pé das encostas do Pisga."},{"id":4,"segments":[{"t":"Tomaram","s":"H1366"},{"t":" o ","s":null},{"t":"território","s":"H4428"},{"t":" ","s":null},{"t":"de","s":"H1316"},{"t":" ","s":null},{"t":"Ogue","s":"H3499"},{"t":", ","s":null},{"t":"rei","s":"H7497"},{"t":" de ","s":null},{"t":"Basã","s":"H154"},{"t":", um dos últimos refains, que reinou ","s":null},{"t":"em","s":"H3427"},{"t":" ","s":null},{"t":"Asterote","s":"H6252"},{"t":" e Edrei.","s":null}],"text":"Tomaram o território de Ogue, rei de Basã, um dos últimos refains, que reinou em Asterote e Edrei."},{"id":5,"segments":[{"t":"Ele","s":"H4910"},{"t":" ","s":null},{"t":"governou","s":"H2809"},{"t":" o ","s":null},{"t":"monte","s":"H1568"},{"t":" ","s":null},{"t":"Hermom","s":"H2768"},{"t":", ","s":null},{"t":"Salcá","s":"H5548"},{"t":", ","s":null},{"t":"toda","s":"H3605"},{"t":" a ","s":null},{"t":"Basã","s":"H1651"},{"t":", ","s":null},{"t":"até","s":"H5704"},{"t":" a ","s":null},{"t":"fronteira","s":"H1366"},{"t":" ","s":null},{"t":"do","s":"H5511"},{"t":" povo de ","s":null},{"t":"Gesur","s":"H2677"},{"t":" e de Maaca, e metade de Gileade, até a fronteira de ","s":null},{"t":"Seom","s":"H4428"},{"t":", rei de Hesbom.","s":null}],"text":"Ele governou o monte Hermom, Salcá, toda a Basã, até a fronteira do povo de Gesur e de Maaca, e metade de Gileade, até a fronteira de Seom, rei de Hesbom."},{"id":6,"segments":[{"t":"Moisés","s":"H4872"},{"t":", ","s":null},{"t":"servo","s":"H5650"},{"t":" ","s":null},{"t":"do","s":"H1121"},{"t":" ","s":null},{"t":"Senhor","s":"H3068"},{"t":", e ","s":null},{"t":"os","s":"H1425"},{"t":" ","s":null},{"t":"israelitas","s":"H2677"},{"t":" os ","s":null},{"t":"derrotaram","s":"H5221"},{"t":". ","s":null},{"t":"E","s":"H4519"},{"t":" Moisés, servo do Senhor, ","s":null},{"t":"deu","s":"H5414"},{"t":" a ","s":null},{"t":"terra","s":"H776"},{"t":" deles como propriedade às tribos de Rúben, de Gade e à metade da tribo de Manassés.","s":null}],"text":"Moisés, servo do Senhor, e os israelitas os derrotaram. E Moisés, servo do Senhor, deu a terra deles como propriedade às tribos de Rúben, de Gade e à metade da tribo de Manassés."},{"id":7,"segments":[{"t":"São","s":"H428"},{"t":" ","s":null},{"t":"estes","s":"H1121"},{"t":" ","s":null},{"t":"os","s":"H834"},{"t":" ","s":null},{"t":"reis","s":"H4428"},{"t":" ","s":null},{"t":"que","s":"H3383"},{"t":" ","s":null},{"t":"Josué","s":"H3220"},{"t":" e os ","s":null},{"t":"israelitas","s":"H3091"},{"t":" ","s":null},{"t":"derrotaram","s":"H3844"},{"t":" ","s":null},{"t":"no","s":"H4256"},{"t":" ","s":null},{"t":"lado","s":"H7626"},{"t":" ","s":null},{"t":"ocidental","s":"H5221"},{"t":" do ","s":null},{"t":"Jordão","s":"H3478"},{"t":", desde ","s":null},{"t":"Baal-Gade","s":"H5704"},{"t":", no ","s":null},{"t":"vale","s":"H1171"},{"t":" do Líbano, até o monte Halaque, que ","s":null},{"t":"se","s":"H2022"},{"t":" ","s":null},{"t":"ergue","s":"H2510"},{"t":" ","s":null},{"t":"na","s":"H5927"},{"t":" ","s":null},{"t":"direção","s":"H8165"},{"t":" de Seir. Josué deu a ","s":null},{"t":"terra","s":"H776"},{"t":" deles por herança às ","s":null},{"t":"tribos","s":"H5414"},{"t":" de ","s":null},{"t":"Israel","s":"H3425"},{"t":", repartindo-a entre elas —","s":null}],"text":"São estes os reis que Josué e os israelitas derrotaram no lado ocidental do Jordão, desde Baal-Gade, no vale do Líbano, até o monte Halaque, que se ergue na direção de Seir. Josué deu a terra deles por herança às tribos de Israel, repartindo-a entre elas —"},{"id":8,"segments":[{"t":"a","s":"H2022"},{"t":" ","s":null},{"t":"serra","s":"H8219"},{"t":" ","s":null},{"t":"central","s":"H6160"},{"t":", a ","s":null},{"t":"Sefelá","s":"H794"},{"t":", a ","s":null},{"t":"Arabá","s":"H4057"},{"t":", ","s":null},{"t":"as","s":"H5045"},{"t":" ","s":null},{"t":"encostas","s":"H2850"},{"t":" das montanhas, o deserto e o Neguebe — as terras ","s":null},{"t":"dos","s":"H3669"},{"t":" ","s":null},{"t":"hititas","s":"H2983"},{"t":", dos amorreus, dos cananeus, dos ","s":null},{"t":"ferezeus","s":"H567"},{"t":", dos ","s":null},{"t":"heveus","s":"H6522"},{"t":" e dos jebuseus:","s":null}],"text":"a serra central, a Sefelá, a Arabá, as encostas das montanhas, o deserto e o Neguebe — as terras dos hititas, dos amorreus, dos cananeus, dos ferezeus, dos heveus e dos jebuseus:"},{"id":9,"segments":[{"t":"o","s":"H4428"},{"t":" ","s":null},{"t":"rei","s":"H3405"},{"t":" ","s":null},{"t":"de","s":"H5857"},{"t":" ","s":null},{"t":"Jericó","s":"H259"},{"t":", o rei de ","s":null},{"t":"Ai","s":"H834"},{"t":", ","s":null},{"t":"próxima","s":"H6654"},{"t":" a Betel,","s":null}],"text":"o rei de Jericó, o rei de Ai, próxima a Betel,"},{"id":10,"segments":[{"t":"o","s":"H4428"},{"t":" ","s":null},{"t":"rei","s":"H3389"},{"t":" ","s":null},{"t":"de","s":"H2275"},{"t":" ","s":null},{"t":"Jerusalém","s":"H259"},{"t":", o rei de Hebrom,","s":null}],"text":"o rei de Jerusalém, o rei de Hebrom,"},{"id":11,"segments":[{"t":"o","s":"H4428"},{"t":" ","s":null},{"t":"rei","s":"H3412"},{"t":" ","s":null},{"t":"de","s":"H3923"},{"t":" ","s":null},{"t":"Jarmute","s":"H259"},{"t":", o rei de Láquis,","s":null}],"text":"o rei de Jarmute, o rei de Láquis,"},{"id":12,"segments":[{"t":"o","s":"H4428"},{"t":" ","s":null},{"t":"rei","s":"H5700"},{"t":" ","s":null},{"t":"de","s":"H1507"},{"t":" ","s":null},{"t":"Eglom","s":"H259"},{"t":", o rei de Gezer,","s":null}],"text":"o rei de Eglom, o rei de Gezer,"},{"id":13,"segments":[{"t":"o","s":"H4428"},{"t":" ","s":null},{"t":"rei","s":"H1688"},{"t":" ","s":null},{"t":"de","s":"H1445"},{"t":" ","s":null},{"t":"Debir","s":"H259"},{"t":", o rei de Geder,","s":null}],"text":"o rei de Debir, o rei de Geder,"},{"id":14,"segments":[{"t":"o","s":"H4428"},{"t":" ","s":null},{"t":"rei","s":"H2767"},{"t":" ","s":null},{"t":"de","s":"H6166"},{"t":" ","s":null},{"t":"Hormá","s":"H259"},{"t":", o rei de Arade,","s":null}],"text":"o rei de Hormá, o rei de Arade,"},{"id":15,"segments":[{"t":"o","s":"H4428"},{"t":" ","s":null},{"t":"rei","s":"H3841"},{"t":" ","s":null},{"t":"de","s":"H5725"},{"t":" ","s":null},{"t":"Libna","s":"H259"},{"t":", o rei de Adulão,","s":null}],"text":"o rei de Libna, o rei de Adulão,"},{"id":16,"segments":[{"t":"o","s":"H4428"},{"t":" ","s":null},{"t":"rei","s":"H4719"},{"t":" ","s":null},{"t":"de","s":"H1008"},{"t":" ","s":null},{"t":"Maquedá","s":"H259"},{"t":", o rei de Betel,","s":null}],"text":"o rei de Maquedá, o rei de Betel,"},{"id":17,"segments":[{"t":"o","s":"H4428"},{"t":" ","s":null},{"t":"rei","s":"H8599"},{"t":" ","s":null},{"t":"de","s":"H2660"},{"t":" ","s":null},{"t":"Tapua","s":"H259"},{"t":", o rei de Héfer,","s":null}],"text":"o rei de Tapua, o rei de Héfer,"},{"id":18,"segments":[{"t":"o","s":"H4428"},{"t":" ","s":null},{"t":"rei","s":"H663"},{"t":" ","s":null},{"t":"de","s":"H8289"},{"t":" ","s":null},{"t":"Afeque","s":"H259"},{"t":", o rei de Lasarom,","s":null}],"text":"o rei de Afeque, o rei de Lasarom,"},{"id":19,"segments":[{"t":"o","s":"H4428"},{"t":" ","s":null},{"t":"rei","s":"H4068"},{"t":" ","s":null},{"t":"de","s":"H2674"},{"t":" ","s":null},{"t":"Madom","s":"H259"},{"t":", o rei de Hazor,","s":null}],"text":"o rei de Madom, o rei de Hazor,"},{"id":20,"segments":[{"t":"o","s":"H4428"},{"t":" ","s":null},{"t":"rei","s":"H8112"},{"t":" ","s":null},{"t":"de","s":"H407"},{"t":" ","s":null},{"t":"Sinrom-Merom","s":"H259"},{"t":", o rei de Acsafe,","s":null}],"text":"o rei de Sinrom-Merom, o rei de Acsafe,"},{"id":21,"segments":[{"t":"o","s":"H4428"},{"t":" ","s":null},{"t":"rei","s":"H8590"},{"t":" ","s":null},{"t":"de","s":"H4023"},{"t":" ","s":null},{"t":"Taanaque","s":"H259"},{"t":", o rei de Megido,","s":null}],"text":"o rei de Taanaque, o rei de Megido,"},{"id":22,"segments":[{"t":"o","s":"H4428"},{"t":" ","s":null},{"t":"rei","s":"H3362"},{"t":" ","s":null},{"t":"de","s":"H6943"},{"t":" ","s":null},{"t":"Quedes","s":"H259"},{"t":", o rei de ","s":null},{"t":"Jocneão","s":"H3760"},{"t":" do Carmelo,","s":null}],"text":"o rei de Quedes, o rei de Jocneão do Carmelo,"},{"id":23,"segments":[{"t":"o","s":"H4428"},{"t":" ","s":null},{"t":"rei","s":"H1756"},{"t":" ","s":null},{"t":"de","s":"H259"},{"t":" ","s":null},{"t":"Dor","s":"H1471"},{"t":" ","s":null},{"t":"em","s":"H1537"},{"t":" Nafote-Dor, o rei de Goim de Gilgal,","s":null}],"text":"o rei de Dor em Nafote-Dor, o rei de Goim de Gilgal,"},{"id":24,"segments":[{"t":"e","s":"H4428"},{"t":" o ","s":null},{"t":"rei","s":"H8656"},{"t":" de ","s":null},{"t":"Tirza","s":"H259"},{"t":". ","s":null},{"t":"Trinta","s":"H7970"},{"t":" e um ","s":null},{"t":"reis","s":"H3605"},{"t":" ao todo.","s":null}],"text":"e o rei de Tirza. Trinta e um reis ao todo."}]},"ar":{"verses":[{"id":1,"segments":[{"t":"وهؤلاء","s":"H428"},{"t":" ","s":null},{"t":"هم","s":"H776"},{"t":" ","s":null},{"t":"ملوك","s":"H4428"},{"t":" ","s":null},{"t":"الارض","s":"H1121"},{"t":" ","s":null},{"t":"الذين","s":"H3383"},{"t":" ","s":null},{"t":"ضربهم","s":"H4217"},{"t":" ","s":null},{"t":"بنو","s":"H769"},{"t":" ","s":null},{"t":"اسرائيل","s":"H6160"},{"t":" ","s":null},{"t":"وامتلكوا","s":"H5221"},{"t":" ","s":null},{"t":"ارضهم","s":"H834"},{"t":" في ","s":null},{"t":"عبر","s":"H3423"},{"t":" الاردن ","s":null},{"t":"نحو","s":"H5676"},{"t":" شروق ","s":null},{"t":"الشمس","s":"H5704"},{"t":" من وادي ارنون ","s":null},{"t":"الى","s":"H5158"},{"t":" ","s":null},{"t":"جبل","s":"H2022"},{"t":" ","s":null},{"t":"حرمون","s":"H2768"},{"t":" ","s":null},{"t":"وكل","s":"H3605"},{"t":" العربة نحو الشروق.","s":null}],"text":"وهؤلاء هم ملوك الارض الذين ضربهم بنو اسرائيل وامتلكوا ارضهم في عبر الاردن نحو شروق الشمس من وادي ارنون الى جبل حرمون وكل العربة نحو الشروق."},{"id":2,"segments":[{"t":"سيحون","s":"H5511"},{"t":" ","s":null},{"t":"ملك","s":"H4428"},{"t":" ","s":null},{"t":"الاموريين","s":"H567"},{"t":" ","s":null},{"t":"الساكن","s":"H3427"},{"t":" ","s":null},{"t":"في","s":"H2809"},{"t":" ","s":null},{"t":"حشبون","s":"H4910"},{"t":" ","s":null},{"t":"المتسلط","s":"H6177"},{"t":" ","s":null},{"t":"من","s":"H8193"},{"t":" ","s":null},{"t":"عروعير","s":"H5921"},{"t":" ","s":null},{"t":"التي","s":"H769"},{"t":" ","s":null},{"t":"على","s":"H8432"},{"t":" ","s":null},{"t":"حافة","s":"H5158"},{"t":" ","s":null},{"t":"وادي","s":"H2999"},{"t":" ","s":null},{"t":"ارنون","s":"H1366"},{"t":" ","s":null},{"t":"ووسط","s":"H1121"},{"t":" ","s":null},{"t":"الوادي","s":"H5704"},{"t":" ","s":null},{"t":"ونصف","s":"H1568"},{"t":" جلعاد الى وادي ","s":null},{"t":"يب","s":"H5983"},{"t":"ّ","s":null},{"t":"وق","s":"H2677"},{"t":" تخوم بني عمون","s":null}],"text":"سيحون ملك الاموريين الساكن في حشبون المتسلط من عروعير التي على حافة وادي ارنون ووسط الوادي ونصف جلعاد الى وادي يبّوق تخوم بني عمون"},{"id":3,"segments":[{"t":"والعربة","s":"H6160"},{"t":" ","s":null},{"t":"الى","s":"H3220"},{"t":" ","s":null},{"t":"بحر","s":"H4217"},{"t":" ","s":null},{"t":"كن","s":"H3672"},{"t":"ّ","s":null},{"t":"روت","s":"H794"},{"t":" ","s":null},{"t":"نحو","s":"H6449"},{"t":" الشروق والى بحر العربة بحر الملح نحو الشروق طريق بيت ","s":null},{"t":"يشيموت","s":"H1020"},{"t":" ","s":null},{"t":"ومن","s":"H1870"},{"t":" ","s":null},{"t":"التيمن","s":"H8486"},{"t":" ","s":null},{"t":"تحت","s":"H8478"},{"t":" سفوح الفسجة.","s":null}],"text":"والعربة الى بحر كنّروت نحو الشروق والى بحر العربة بحر الملح نحو الشروق طريق بيت يشيموت ومن التيمن تحت سفوح الفسجة."},{"id":4,"segments":[{"t":"وتخوم","s":"H1366"},{"t":" ","s":null},{"t":"عوج","s":"H5747"},{"t":" ","s":null},{"t":"ملك","s":"H4428"},{"t":" ","s":null},{"t":"باشان","s":"H1316"},{"t":" ","s":null},{"t":"من","s":"H3499"},{"t":" ","s":null},{"t":"بقية","s":"H7497"},{"t":" ","s":null},{"t":"الرفائيين","s":"H154"},{"t":" الساكن في ","s":null},{"t":"عشتاروث","s":"H3427"},{"t":" ","s":null},{"t":"وفي","s":"H6252"},{"t":" اذرعي","s":null}],"text":"وتخوم عوج ملك باشان من بقية الرفائيين الساكن في عشتاروث وفي اذرعي"},{"id":5,"segments":[{"t":"والمتسلط","s":"H4910"},{"t":" ","s":null},{"t":"على","s":"H2022"},{"t":" ","s":null},{"t":"جبل","s":"H2768"},{"t":" ","s":null},{"t":"حرمون","s":"H5548"},{"t":" ","s":null},{"t":"وسلخة","s":"H3605"},{"t":" ","s":null},{"t":"وعلى","s":"H1316"},{"t":" ","s":null},{"t":"كل","s":"H5704"},{"t":" ","s":null},{"t":"باشان","s":"H1366"},{"t":" ","s":null},{"t":"الى","s":"H1651"},{"t":" ","s":null},{"t":"تخم","s":"H4602"},{"t":" ","s":null},{"t":"الجشوريين","s":"H2677"},{"t":" ","s":null},{"t":"والمعكيين","s":"H1568"},{"t":" ","s":null},{"t":"ونصف","s":"H5511"},{"t":" ","s":null},{"t":"جلعاد","s":"H2809"},{"t":" تخوم ","s":null},{"t":"سيحون","s":"H4428"},{"t":" ملك حشبون.","s":null}],"text":"والمتسلط على جبل حرمون وسلخة وعلى كل باشان الى تخم الجشوريين والمعكيين ونصف جلعاد تخوم سيحون ملك حشبون."},{"id":6,"segments":[{"t":"موسى","s":"H4872"},{"t":" ","s":null},{"t":"عبد","s":"H5650"},{"t":" ","s":null},{"t":"الرب","s":"H3068"},{"t":" ","s":null},{"t":"وبنو","s":"H1121"},{"t":" ","s":null},{"t":"اسرائيل","s":"H5221"},{"t":" ","s":null},{"t":"ضربوها","s":"H3425"},{"t":" ","s":null},{"t":"واعطاها","s":"H5414"},{"t":" موسى عبد الرب ","s":null},{"t":"ميراثا","s":"H7206"},{"t":" ","s":null},{"t":"للرأوبينيين","s":"H1425"},{"t":" ","s":null},{"t":"والجاديين","s":"H2677"},{"t":" ","s":null},{"t":"ولنصف","s":"H4519"},{"t":" سبط منسّى","s":null}],"text":"موسى عبد الرب وبنو اسرائيل ضربوها واعطاها موسى عبد الرب ميراثا للرأوبينيين والجاديين ولنصف سبط منسّى"},{"id":7,"segments":[{"t":"وهؤلاء","s":"H428"},{"t":" ","s":null},{"t":"هم","s":"H776"},{"t":" ","s":null},{"t":"ملوك","s":"H4428"},{"t":" ","s":null},{"t":"الارض","s":"H1121"},{"t":" ","s":null},{"t":"الذين","s":"H3383"},{"t":" ","s":null},{"t":"ضربهم","s":"H834"},{"t":" ","s":null},{"t":"يشوع","s":"H3091"},{"t":" ","s":null},{"t":"وبنو","s":"H3220"},{"t":" ","s":null},{"t":"اسرائيل","s":"H5221"},{"t":" ","s":null},{"t":"في","s":"H5676"},{"t":" ","s":null},{"t":"عبر","s":"H1237"},{"t":" ","s":null},{"t":"الاردن","s":"H3844"},{"t":" ","s":null},{"t":"غربا","s":"H5704"},{"t":" ","s":null},{"t":"من","s":"H1171"},{"t":" ","s":null},{"t":"بعل","s":"H4256"},{"t":" ","s":null},{"t":"جاد","s":"H7626"},{"t":" في ","s":null},{"t":"بقعة","s":"H2510"},{"t":" ","s":null},{"t":"لبنان","s":"H2022"},{"t":" ","s":null},{"t":"الى","s":"H5927"},{"t":" ","s":null},{"t":"الجبل","s":"H8165"},{"t":" ","s":null},{"t":"الاقرع","s":"H3478"},{"t":" الصاعد الى سعير. واعطاها يشوع ","s":null},{"t":"لاسباط","s":"H5414"},{"t":" اسرائيل ","s":null},{"t":"ميراثا","s":"H3425"},{"t":" حسب فرقهم.","s":null}],"text":"وهؤلاء هم ملوك الارض الذين ضربهم يشوع وبنو اسرائيل في عبر الاردن غربا من بعل جاد في بقعة لبنان الى الجبل الاقرع الصاعد الى سعير. واعطاها يشوع لاسباط اسرائيل ميراثا حسب فرقهم."},{"id":8,"segments":[{"t":"في","s":"H2022"},{"t":" ","s":null},{"t":"الجبل","s":"H8219"},{"t":" ","s":null},{"t":"والسهل","s":"H6160"},{"t":" ","s":null},{"t":"والعربة","s":"H794"},{"t":" ","s":null},{"t":"والسفوح","s":"H4057"},{"t":" ","s":null},{"t":"والبرية","s":"H5045"},{"t":" ","s":null},{"t":"والجنوب","s":"H2850"},{"t":" الحثّ","s":null},{"t":"يون","s":"H3669"},{"t":" ","s":null},{"t":"والاموريون","s":"H2983"},{"t":" والكنعانيون ","s":null},{"t":"والفرز","s":"H6522"},{"t":"ّيون ","s":null},{"t":"والحو","s":"H567"},{"t":"ّيون ","s":null},{"t":"واليبوسيون","s":"H2340"},{"t":".","s":null}],"text":"في الجبل والسهل والعربة والسفوح والبرية والجنوب الحثّيون والاموريون والكنعانيون والفرزّيون والحوّيون واليبوسيون."},{"id":9,"segments":[{"t":"ملك","s":"H4428"},{"t":" ","s":null},{"t":"اريحا","s":"H3405"},{"t":" ","s":null},{"t":"واحد","s":"H259"},{"t":". ملك ","s":null},{"t":"عاي","s":"H5857"},{"t":" التي ","s":null},{"t":"بجانب","s":"H834"},{"t":" ","s":null},{"t":"بيت","s":"H6654"},{"t":" ","s":null},{"t":"ايل","s":"H1008"},{"t":" واحد.","s":null}],"text":"ملك اريحا واحد. ملك عاي التي بجانب بيت ايل واحد."},{"id":10,"segments":[{"t":"ملك","s":"H4428"},{"t":" ","s":null},{"t":"اورشليم","s":"H3389"},{"t":" ","s":null},{"t":"واحد","s":"H259"},{"t":". ملك ","s":null},{"t":"حبرون","s":"H2275"},{"t":" واحد.","s":null}],"text":"ملك اورشليم واحد. ملك حبرون واحد."},{"id":11,"segments":[{"t":"ملك","s":"H4428"},{"t":" ","s":null},{"t":"يرموت","s":"H3412"},{"t":" ","s":null},{"t":"واحد","s":"H259"},{"t":". ملك ","s":null},{"t":"لخيش","s":"H3923"},{"t":" واحد.","s":null}],"text":"ملك يرموت واحد. ملك لخيش واحد."},{"id":12,"segments":[{"t":"ملك","s":"H4428"},{"t":" ","s":null},{"t":"عجلون","s":"H5700"},{"t":" ","s":null},{"t":"واحد","s":"H259"},{"t":". ملك ","s":null},{"t":"جازر","s":"H1507"},{"t":" واحد.","s":null}],"text":"ملك عجلون واحد. ملك جازر واحد."},{"id":13,"segments":[{"t":"ملك","s":"H4428"},{"t":" ","s":null},{"t":"دبير","s":"H1688"},{"t":" ","s":null},{"t":"واحد","s":"H259"},{"t":". ملك ","s":null},{"t":"جادر","s":"H1445"},{"t":" واحد.","s":null}],"text":"ملك دبير واحد. ملك جادر واحد."},{"id":14,"segments":[{"t":"ملك","s":"H4428"},{"t":" ","s":null},{"t":"حرمة","s":"H2767"},{"t":" ","s":null},{"t":"واحد","s":"H259"},{"t":". ملك ","s":null},{"t":"عراد","s":"H6166"},{"t":" واحد.","s":null}],"text":"ملك حرمة واحد. ملك عراد واحد."},{"id":15,"segments":[{"t":"ملك","s":"H4428"},{"t":" ","s":null},{"t":"لبنة","s":"H3841"},{"t":" ","s":null},{"t":"واحد","s":"H259"},{"t":". ملك ","s":null},{"t":"عدلام","s":"H5725"},{"t":" واحد.","s":null}],"text":"ملك لبنة واحد. ملك عدلام واحد."},{"id":16,"segments":[{"t":"ملك","s":"H4428"},{"t":" ","s":null},{"t":"مقيدة","s":"H4719"},{"t":" ","s":null},{"t":"واحد","s":"H259"},{"t":". ملك ","s":null},{"t":"بيت","s":"H1008"},{"t":" ايل واحد.","s":null}],"text":"ملك مقيدة واحد. ملك بيت ايل واحد."},{"id":17,"segments":[{"t":"ملك","s":"H4428"},{"t":" ","s":null},{"t":"تفوح","s":"H8599"},{"t":" ","s":null},{"t":"واحد","s":"H259"},{"t":". ملك ","s":null},{"t":"حافر","s":"H2660"},{"t":" واحد.","s":null}],"text":"ملك تفوح واحد. ملك حافر واحد."},{"id":18,"segments":[{"t":"ملك","s":"H4428"},{"t":" ","s":null},{"t":"افيق","s":"H663"},{"t":" ","s":null},{"t":"واحد","s":"H259"},{"t":" ملك ","s":null},{"t":"لش","s":"H8289"},{"t":"ّارون واحد.","s":null}],"text":"ملك افيق واحد ملك لشّارون واحد."},{"id":19,"segments":[{"t":"ملك","s":"H4428"},{"t":" ","s":null},{"t":"مادون","s":"H4068"},{"t":" ","s":null},{"t":"واحد","s":"H259"},{"t":". ملك ","s":null},{"t":"حاصور","s":"H2674"},{"t":" واحد.","s":null}],"text":"ملك مادون واحد. ملك حاصور واحد."},{"id":20,"segments":[{"t":"ملك","s":"H4428"},{"t":" ","s":null},{"t":"شمرون","s":"H8112"},{"t":" ","s":null},{"t":"مرأون","s":"H259"},{"t":" ","s":null},{"t":"واحد","s":"H407"},{"t":". ملك اكشاف واحد.","s":null}],"text":"ملك شمرون مرأون واحد. ملك اكشاف واحد."},{"id":21,"segments":[{"t":"ملك","s":"H4428"},{"t":" ","s":null},{"t":"تعنك","s":"H8590"},{"t":" ","s":null},{"t":"واحد","s":"H259"},{"t":". ملك ","s":null},{"t":"مجدو","s":"H4023"},{"t":" واحد.","s":null}],"text":"ملك تعنك واحد. ملك مجدو واحد."},{"id":22,"segments":[{"t":"ملك","s":"H4428"},{"t":" ","s":null},{"t":"قادش","s":"H6943"},{"t":" ","s":null},{"t":"واحد","s":"H259"},{"t":". ملك ","s":null},{"t":"يقنعام","s":"H3362"},{"t":" ","s":null},{"t":"في","s":"H3760"},{"t":" كرمل واحد.","s":null}],"text":"ملك قادش واحد. ملك يقنعام في كرمل واحد."},{"id":23,"segments":[{"t":"ملك","s":"H4428"},{"t":" ","s":null},{"t":"دور","s":"H1756"},{"t":" ","s":null},{"t":"في","s":"H1471"},{"t":" ","s":null},{"t":"مرتفعات","s":"H1537"},{"t":" دور ","s":null},{"t":"واحد","s":"H259"},{"t":". ملك جوييم في الجلجال واحد.","s":null}],"text":"ملك دور في مرتفعات دور واحد. ملك جوييم في الجلجال واحد."},{"id":24,"segments":[{"t":"ملك","s":"H4428"},{"t":" ","s":null},{"t":"ترصة","s":"H8656"},{"t":" ","s":null},{"t":"واحد","s":"H259"},{"t":". ","s":null},{"t":"جميع","s":"H7970"},{"t":" ","s":null},{"t":"الملوك","s":"H3605"},{"t":" واحد وثلاثون","s":null}],"text":"ملك ترصة واحد. جميع الملوك واحد وثلاثون"}]}}